MANIFEST.in
README.rst
setup.py
Spectrum2/__init__.py
Spectrum2/backend.py
Spectrum2/iochannel.py
Spectrum2/protocol_pb2.py
transWhat/__init__.py
transWhat/bot.py
transWhat/buddy.py
transWhat/deferred.py
transWhat/group.py
transWhat/registersession.py
transWhat/session.py
transWhat/threadutils.py
transWhat/transwhat.py
transWhat/utils.py
transWhat/whatsappbackend.py
transWhat/yowsupwrapper.py
transwhat.egg-info/PKG-INFO
transwhat.egg-info/SOURCES.txt
transwhat.egg-info/dependency_links.txt
transwhat.egg-info/entry_points.txt
transwhat.egg-info/not-zip-safe
transwhat.egg-info/requires.txt
transwhat.egg-info/top_level.txt