Metadata-Version: 1.1
Name: transwhat
Version: 0.2.2
Summary: A gateway between the XMPP and the WhatsApp IM networks
Home-page: https://github.com/stv0g/transwhat
Author: Steffen Vogel
Author-email: stv0g@0l.de
License: GPL-3+
Keywords: whatsapp xmpp im gateway transport yowsup
Platform: UNKNOWN
Classifier: License :: OSI Approved :: GNU General Public License v3 or later (GPLv3+)
Classifier: Development Status :: 4 - Beta
Classifier: Environment :: Plugins
Classifier: Operating System :: POSIX
Classifier: Topic :: Communications :: Chat
